sound_track_extract/__init__.py
sound_track_extract/cli.py
sound_track_extract-0.1.0.dist-info/METADATA
sound_track_extract-0.1.0.dist-info/WHEEL
sound_track_extract-0.1.0.dist-info/entry_points.txt
sound_track_extract-0.1.0.dist-info/top_level.txt
sound_track_extract-0.1.0.dist-info/RECORD
