Metadata-Version: 2.4
Name: sound-track-extract
Version: 0.1.0
Summary: Tiny CLI to extract and tag audio tracks from video files via ffmpeg.
Requires-Python: >=3.13
Requires-Dist: typer>=0.12.3
Requires-Dist: rich>=13.7.1
Provides-Extra: dev
Requires-Dist: pytest>=8.3.3; extra == "dev"
